MANIFEST.in
README.txt
setup.py
o2w/__init__.py
o2w/cache_invalidator/__init__.py
o2w_cache_invalidator.egg-info/PKG-INFO
o2w_cache_invalidator.egg-info/SOURCES.txt
o2w_cache_invalidator.egg-info/dependency_links.txt
o2w_cache_invalidator.egg-info/top_level.txt