Metadata-Version: 1.0
Name: o2w-cache-invalidator
Version: 0.0.1
Summary: Invalidades varnish cache and memcached
Home-page: http://www.o2w.es/
Author: José Sánchez Moreno
Author-email: jose@o2w.es
License: LICENSE.txt
Platform: UNKNOWN
